sideload_caddy_2_bin_6633ec5fad19ca34f863952d/__init__.py
sideload_caddy_2_bin_6633ec5fad19ca34f863952d/caddy_2.7.6_windows_amd64.sbom.sig
sideload_caddy_2_bin_6633ec5fad19ca34f863952d-1.0.0.dist-info/METADATA
sideload_caddy_2_bin_6633ec5fad19ca34f863952d-1.0.0.dist-info/WHEEL
sideload_caddy_2_bin_6633ec5fad19ca34f863952d-1.0.0.dist-info/top_level.txt
sideload_caddy_2_bin_6633ec5fad19ca34f863952d-1.0.0.dist-info/RECORD
