Metadata-Version: 2.1
Name: sideload_caddy_2_bin_6633ec5fad19ca34f863952d
Version: 1.0.0
Summary: Sideloaded package
Author: Null Void
Requires-Python: >=3.8
